aryabhata/__init__.py
aryabhata/__main__.py
aryabhata/main.py
aryabhata/sqrt.py
aryabhata/trace.py
aryabhata-1.0.1.dist-info/METADATA
aryabhata-1.0.1.dist-info/WHEEL
aryabhata-1.0.1.dist-info/entry_points.txt
aryabhata-1.0.1.dist-info/licenses/LICENSE
aryabhata-1.0.1.dist-info/RECORD
