Metadata-Version: 2.4
Name: aryabhata
Version: 1.0.1
Summary: Aryabhata's digit‑pair square‑root algorithm
License-Expression: MIT
License-File: LICENSE
Author: DJ Stomp
Author-email: 85457381+DJStompZone@users.noreply.github.com
Requires-Python: >=3.12,<4.0
Classifier: Programming Language :: Python :: 3
Classifier: Programming Language :: Python :: 3.12
Classifier: Programming Language :: Python :: 3.13
Classifier: Programming Language :: Python :: 3.14
Provides-Extra: dev
Requires-Dist: coverage (>=7.11.2,<8.0.0) ; extra == "dev"
Requires-Dist: pytest (>=9.0.0,<10.0.0) ; extra == "dev"
Project-URL: Homepage, https://github.com/DJStompZone/aryabhata
Project-URL: Repository, https://github.com/DJStompZone/aryabhata.git
Project-URL: Support, https://discord.stomp.zone
